nonebot_plugin_witff/__init__.py
nonebot_plugin_witff/templates/help.html
nonebot_plugin_witff/templates/witff.html
nonebot_plugin_witff-0.3.1.dist-info/WHEEL
nonebot_plugin_witff-0.3.1.dist-info/METADATA
nonebot_plugin_witff-0.3.1.dist-info/licenses/LICENSE
nonebot_plugin_witff-0.3.1.dist-info/RECORD
