Metadata-Version: 2.1
Name: nonebot_plugin_witff
Version: 0.3.1
Summary: 兽聚是什么时候? | 兽聚时间查询插件
License: MIT
Author-email: Kcy7 <thunder@furry-owo.top>
Requires-Python: >=3.9
Requires-Dist: httpx>=0.23.0
Requires-Dist: nonebot-adapter-onebot>=2.0.0
Requires-Dist: nonebot-plugin-htmlrender>=0.6.6
Requires-Dist: nonebot2>=2.0.0
